qosic/__init__.py
qosic/client.py
qosic/errors.py
qosic/logger.py
qosic/mobile_carriers/__init__.py
qosic/mobile_carriers/bj/__init__.py
qosic/mobile_carriers/bj/moov.py
qosic/mobile_carriers/bj/mtn.py
qosic/mobile_carriers/bj/mtn_.py
qosic/mobile_carriers/utils.py
qosic/protocols.py
qosic/py.typed
qosic/utils.py
qosic_sdk-5.0.1.dist-info/LICENSE
qosic_sdk-5.0.1.dist-info/METADATA
qosic_sdk-5.0.1.dist-info/WHEEL
qosic_sdk-5.0.1.dist-info/RECORD
