Metadata-Version: 2.1
Name: qosic-sdk
Version: 5.0.1
Summary: An unofficial python sdk for the QosIc platform.
Home-page: https://github.com/Tobi-De/qosic-sdk
License: MIT
Keywords: python,qosic-sdk,qosic,qos,payment,momo,mobile money
Author: Tobi-De
Author-email: tobidegnon@protonmail.com
Requires-Python: >=3.8,<4.0
Classifier: Development Status :: 5 - Production/Stable
Classifier: Intended Audience :: Developers
Classifier: License :: OSI Approved :: MIT License
Classifier: Natural Language :: English
Classifier: Programming Language :: Python :: 3
Classifier: Programming Language :: Python :: 3.8
Classifier: Programming Language :: Python :: 3.9
Classifier: Programming Language :: Python :: 3.10
Classifier: Programming Language :: Python :: 3.11
Classifier: Programming Language :: Python :: 3 :: Only
Requires-Dist: httpx (>=0.24.0,<0.25.0)
Requires-Dist: polling2 (>=0.5.0,<0.6.0)
Requires-Dist: shibuya (>=2023.3.19,<2024.0.0)
Project-URL: Repository, https://github.com/Tobi-De/qosic-sdk
